poverlap/__init__.py
poverlap/point_circle.py
poverlap/point_line.py
poverlap/point_point.py
poverlap/point_polygon.py
poverlap/point_rectangle.py
poverlap/point_triangle.py
poverlap-1.0.0.dist-info/License
poverlap-1.0.0.dist-info/METADATA
poverlap-1.0.0.dist-info/WHEEL
poverlap-1.0.0.dist-info/top_level.txt
poverlap-1.0.0.dist-info/RECORD
