Metadata-Version: 2.1
Name: poverlap
Version: 1.0.0
Summary: Point Overlapping With Any 2D Shape
Author-email: Tooraj <booleansfunction@Gmail.com>
License: Copyright (c) <2025> <Tooraj - booleansfunction@Gmail.com>
Project-URL: Homepage, https://github.com/IRTJ/poverlap
Project-URL: Source, https://github.com/IRTJ/poverlap
Keywords: point,overlapping,collide,2d overlap,2d collide,collision,overlap,point overlap,point collide
Classifier: Development Status :: 4 - Beta
Classifier: Intended Audience :: Developers
Classifier: Topic :: Software Development :: Build Tools
Classifier: Topic :: Software Development :: Libraries :: Python Modules
Classifier: License :: OSI Approved :: MIT License
Classifier: Programming Language :: Python :: 3
Classifier: Programming Language :: Python :: 3.9
Classifier: Programming Language :: Python :: 3.10
Classifier: Programming Language :: Python :: 3.11
Classifier: Programming Language :: Python :: 3 :: Only
Requires-Python: >=3.9
License-File: License
